jsonexus/__init__.py
jsonexus-1.0.3.dist-info/METADATA
jsonexus-1.0.3.dist-info/WHEEL
jsonexus-1.0.3.dist-info/top_level.txt
jsonexus-1.0.3.dist-info/RECORD
