Metadata-Version: 2.1
Name: jsonexus
Version: 1.0.3
Summary: JSONexus is a lightweight and flexible database solution designed for modern applications. It provides a simple and intuitive way to store, query, and manipulate data using JSON documents.
Home-page: https://github.com/rakibma7254/jsonexus
Author: Rakib Hossain
Author-email: rakib4ggp@gmail.com
License: MIT
Keywords: json-database
Classifier: License :: OSI Approved :: MIT License
Classifier: Programming Language :: Python :: 3
Classifier: Programming Language :: Python :: 3.6
Requires-Dist: orjson
